zktop.py
zktop-1.0.0.dist-info/DESCRIPTION.rst
zktop-1.0.0.dist-info/METADATA
zktop-1.0.0.dist-info/RECORD
zktop-1.0.0.dist-info/WHEEL
zktop-1.0.0.dist-info/entry_points.txt
zktop-1.0.0.dist-info/metadata.json
zktop-1.0.0.dist-info/top_level.txt
