Metadata-Version: 2.0
Name: zktop
Version: 1.0.0
Summary: top for Apache ZooKeeper
Home-page: https://github.com/phunt/zktop
Author: Patrick Hunt
Author-email: phunt1@gmail.com
License: Apache v2
Keywords: zookeeper top monitoring
Platform: UNKNOWN
Classifier: Development Status :: 5 - Production/Stable
Classifier: Intended Audience :: System Administrators
Classifier: Topic :: System :: Monitoring
Classifier: License :: OSI Approved :: Apache Software License
Classifier: Programming Language :: Python :: 2
Classifier: Programming Language :: Python :: 3
Requires-Python: >=2.6
